odoo/addons/hr_employee_group_overview_readonly/README.rst
odoo/addons/hr_employee_group_overview_readonly/__init__.py
odoo/addons/hr_employee_group_overview_readonly/__manifest__.py
odoo/addons/hr_employee_group_overview_readonly/i18n/hr_employee_group_overview_readonly.pot
odoo/addons/hr_employee_group_overview_readonly/i18n/it.po
odoo/addons/hr_employee_group_overview_readonly/models/__init__.py
odoo/addons/hr_employee_group_overview_readonly/models/hr_employee.py
odoo/addons/hr_employee_group_overview_readonly/readme/CONTRIBUTORS.rst
odoo/addons/hr_employee_group_overview_readonly/readme/DESCRIPTION.rst
odoo/addons/hr_employee_group_overview_readonly/readme/USAGE.rst
odoo/addons/hr_employee_group_overview_readonly/security/hr_employee_security.xml
odoo/addons/hr_employee_group_overview_readonly/security/ir.model.access.csv
odoo/addons/hr_employee_group_overview_readonly/static/description/icon.png
odoo/addons/hr_employee_group_overview_readonly/static/description/index.html
odoo/addons/hr_employee_group_overview_readonly/views/hr_employee_views.xml
odoo_addon_hr_employee_group_overview_readonly-16.0.1.0.0.10.dist-info/METADATA
odoo_addon_hr_employee_group_overview_readonly-16.0.1.0.0.10.dist-info/WHEEL
odoo_addon_hr_employee_group_overview_readonly-16.0.1.0.0.10.dist-info/top_level.txt
odoo_addon_hr_employee_group_overview_readonly-16.0.1.0.0.10.dist-info/RECORD
